{
  "type": "GepPromptArtifact",
  "at": "2026-03-21T05:04:12.947Z",
  "cycle_id": "Cycle #0214",
  "run_id": "run_1774069452776",
  "prompt_path": "C:\\Users\\Haide\\.openclaw\\workspace\\memory\\evolution\\gep_prompt_Cycle_#0214_run_1774069452776.txt",
  "meta": {
    "agent": "main",
    "drift_enabled": false,
    "review_mode": true,
    "dry_run": false,
    "mutation_id": "mut_1774069452767",
    "personality_key": "rigor=0.7|creativity=0.3|verbosity=0.3|risk_tolerance=0.4|obedience=0.9"
  }
}
